is_port_free/__init__.py
is_port_free/cli.py
is_port_free-1.0.0.dist-info/METADATA
is_port_free-1.0.0.dist-info/WHEEL
is_port_free-1.0.0.dist-info/entry_points.txt
is_port_free-1.0.0.dist-info/top_level.txt
is_port_free-1.0.0.dist-info/RECORD
